gm_pymms/Timer.py
gm_pymms/__init__.py
gm_pymms/driver_audio.py
gm_pymms/driver_sounddevice_audio.py
gm_pymms/driver_termux_audio.py
gm_pymms/noise_filter.py
gm_pymms/pymms.py
gm_pymms/termplayer.py
gm_pymms-0.0.3.data/scripts/pymms
gm_pymms-0.0.3.dist-info/LICENSE
gm_pymms-0.0.3.dist-info/METADATA
gm_pymms-0.0.3.dist-info/WHEEL
gm_pymms-0.0.3.dist-info/top_level.txt
gm_pymms-0.0.3.dist-info/RECORD
