Metadata-Version: 2.1
Name: gm-pymms
Version: 0.0.3
Summary: python xmms inspired media player/recorder
Home-page: https://github.com/gretchycat/pymms
Author: Gretchen Maculo
Author-email: gretchen.maculo@gmail.com
License: GPL3
Classifier: Programming Language :: Python :: 3
Classifier: License :: OSI Approved :: GNU General Public License v3 (GPLv3)
Classifier: Operating System :: OS Independent
Classifier: Environment :: Console
Requires-Python: >=3.6
License-File: LICENSE
Requires-Dist: pydub
Requires-Dist: gm-termcontrol
